README.rst
setup.py
expresscheckout/Cards.py
expresscheckout/Orders.py
expresscheckout/Payments.py
expresscheckout/SampleTest.py
expresscheckout/Test.py
expresscheckout/__init__.py
expresscheckout/config.py
expresscheckout/util.py
expresscheckout.egg-info/PKG-INFO
expresscheckout.egg-info/SOURCES.txt
expresscheckout.egg-info/dependency_links.txt
expresscheckout.egg-info/requires.txt
expresscheckout.egg-info/top_level.txt