Metadata-Version: 1.1
Name: expresscheckout
Version: 1.0.4
Summary:  A Python package for interacting with the Juspay Express Checkout API
Home-page: https://www.juspay.in 
Author: juspay
Author-email: support@juspay.in
License: MIT
Keywords: juspay expresscheckout payments
Platform: UNKNOWN
Classifier: Development Status :: 4 - Beta
Classifier: Intended Audience :: Developers
Classifier: License :: OSI Approved :: MIT License
Classifier: Programming Language :: Python :: 2
Classifier: Programming Language :: Python :: 2.6
Classifier: Programming Language :: Python :: 2.7
Classifier: Programming Language :: Python :: 3
Classifier: Programming Language :: Python :: 3.3
Classifier: Programming Language :: Python :: 3.4
Classifier: Programming Language :: Python :: 3.5
